pl_devtools/__about__.py
pl_devtools/__init__.py
pl_devtools/__main__.py
pl_devtools/dependencies.py
lightning_devtools-0.1.0.dev0.dist-info/LICENSE
lightning_devtools-0.1.0.dev0.dist-info/METADATA
lightning_devtools-0.1.0.dev0.dist-info/WHEEL
lightning_devtools-0.1.0.dev0.dist-info/top_level.txt
lightning_devtools-0.1.0.dev0.dist-info/RECORD
