Metadata-Version: 2.1
Name: lightning-devtools
Version: 0.1.0.dev0
Summary: PyTorch Lightning Sample project.
Home-page: https://github.com/Lightning-AI/dev-toolbox
Author: Lightning AI et al.
Author-email: pytorch@lightning.ai
License: Apache-2.0
Download-URL: https://github.com/Lightning-AI/dev-toolbox
Project-URL: Bug Tracker, https://github.com/Lightning-AI/dev-toolbox/issues
Project-URL: Documentation, https://dev-toolbox.rtfd.io/en/latest/
Project-URL: Source Code, https://github.com/Lightning-AI/dev-toolbox
Keywords: DevOps,CI/CD
Platform: UNKNOWN
Classifier: Environment :: Console
Classifier: Natural Language :: English
Classifier: Development Status :: 3 - Alpha
Classifier: Intended Audience :: Developers
Classifier: Operating System :: OS Independent
Classifier: Programming Language :: Python :: 3
Classifier: Programming Language :: Python :: 3.7
Classifier: Programming Language :: Python :: 3.8
Classifier: Programming Language :: Python :: 3.9
Classifier: Programming Language :: Python :: 3.10
Requires-Python: >=3.7
License-File: LICENSE
Requires-Dist: fire
